st_flexible_callout_elements/__init__.py
st_flexible_callout_elements/flexible_callout.py
st_flexible_callout_elements-0.2.1.dist-info/licenses/LICENSE
st_flexible_callout_elements-0.2.1.dist-info/METADATA
st_flexible_callout_elements-0.2.1.dist-info/WHEEL
st_flexible_callout_elements-0.2.1.dist-info/top_level.txt
st_flexible_callout_elements-0.2.1.dist-info/RECORD
