Metadata-Version: 2.4
Name: st-flexible-callout-elements
Version: 0.2.1
Summary: A Streamlit package for flexible, customizable status elements
Home-page: https://github.com/jlnetosci/st-flexible-callout-elements
Author: João L. Neto
Classifier: Programming Language :: Python :: 3
Classifier: License :: OSI Approved :: MIT License
Classifier: Operating System :: OS Independent
Requires-Python: >=3.6
License-File: LICENSE
Requires-Dist: streamlit>=1.13.0
Dynamic: author
Dynamic: classifier
Dynamic: description
Dynamic: description-content-type
Dynamic: home-page
Dynamic: license-file
Dynamic: requires-dist
Dynamic: requires-python
Dynamic: summary
